Workbook

Sheet Company definition
A1: Personnel | B1: Num | C1: Gross annual salary | D1: annual employment cost | E1: total | H1: Nº | I1: Concept | J1: val | K1: Amount
A2: General manager | B2: 1 | C2: 76243 | D2: 91781.35 | E2: =B2*D2 -> 91781.35 | H2: 1 | I2: Total direct costs | K2: =D24 -> 246372.66
A3: Project manager | B3: 1 | C3: 40550 | D3: 53039.4 | E3: =B3*D3 -> 53039.4 | H3: 2 | I3: Total indirect cotsts | K3: =B75 -> 335500.22
A4: Service coordinator | B4: 1 | C4: 25135 | D4: 32876.58 | E4: =B4*D4 -> 32876.58 | H4: 3 | I4: Sum of direct and indirect costs | K4: =K2+K3 -> 581872.88
A5: Systems analyst | B5: 1 | C5: 35574 | D5: 46530.79 | E5: =B5*D5 -> 46530.79 | H5: 4 | I5: Desired profit | J5: 0.25 | K5: =K4*J5 -> 145468.22
A6: Technology consultant | B6: 1 | C6: 41988 | D6: 54920.3 | E6: =B6*D6 -> 54920.3 | H6: 5 | I6: Required billing/revenue | K6: =K4+K5 -> 727341.1
A7: Software architect | B7: 1 | C7: 44369 | D7: 58034.65 | E7: =B7*D7 -> 58034.65 | H7: 6 | I7: Possible billing based on productive hours and calculated hourly rates | K7: =E90 -> 781150.64
A8: Senior developer | B8: 2 | C8: 39879 | D8: 52161.73 | E8: =B8*D8 -> 104323.46 | H8: 7 | I8: Margin between total cost and billing | K8: =IFERROR((K7-K6)/K6,"sin valor") -> 0.073981155
A9: Junior developer | B9: 4 | C9: 25872 | D9: 33840.58 | E9: =B9*D9 -> 135362.32
A10: Sales representative | B10: 1 | C10: 26849 | D10: 35118.49 | E10: =B10*D10 -> 35118.49
A11: TOTAL | B11: =SUM(B2:B10) -> 13 | E11: =SUM(E2:E10) -> 611987.34
A14: Personnel | B14: TOTAL | C14: Prod(%) | D14: Direct cost | E14: IC (%) | F14: Indirect cost
A15: General manager | B15: =D2 -> 91781.35 | C15: 0 | D15: =ROUND(B15*C15,2) -> 0 | E15: =1-C15 -> 1 | F15: =ROUND(B15*E15,2) -> 91781.35
A16: Project manager | B16: =D3 -> 53039.4 | C16: 0.65 | D16: =ROUND(B16*C16,2) -> 34475.61 | E16: =1-C16 -> 0.35 | F16: =ROUND(B16*E16,2) -> 18563.79
A17: Service coordinator | B17: =D4 -> 32876.58 | C17: 0.5 | D17: =ROUND(B17*C17,2) -> 16438.29 | E17: =1-C17 -> 0.5 | F17: =ROUND(B17*E17,2) -> 16438.29
A18: Systems analyst | B18: =D5 -> 46530.79 | C18: 0.8 | D18: =ROUND(B18*C18,2) -> 37224.63 | E18: =1-C18 -> 0.2 | F18: =ROUND(B18*E18,2) -> 9306.16
A19: Technology consultant | B19: =D6 -> 54920.3 | C19: 0.85 | D19: =ROUND(B19*C19,2) -> 46682.26 | E19: =1-C19 -> 0.15 | F19: =ROUND(B19*E19,2) -> 8238.05
A20: Software architect | B20: =D7 -> 58034.65 | C20: 0.75 | D20: =ROUND(B20*C20,2) -> 43525.99 | E20: =1-C20 -> 0.25 | F20: =ROUND(B20*E20,2) -> 14508.66
A21: Senior developer | B21: =D8 -> 52161.73 | C21: 0.85 | D21: =ROUND(B21*C21,2) -> 44337.47 | E21: =1-C21 -> 0.15 | F21: =ROUND(B21*E21,2) -> 7824.26
A22: Junior developer | B22: =D9 -> 33840.58 | C22: 0.7 | D22: =ROUND(B22*C22,2) -> 23688.41 | E22: =1-C22 -> 0.3 | F22: =ROUND(B22*E22,2) -> 10152.17
A23: Sales representative | B23: =D10 -> 35118.49 | C23: 0 | D23: =ROUND(B23*C23,2) -> 0 | E23: =1-C23 -> 1 | F23: =ROUND(B23*E23,2) -> 35118.49
A24: TOTAL | B24: =SUM(B15:B23) -> 458303.87 | D24: =SUM(D15:D23) -> 246372.66 | F24: =SUM(F15:F23) -> 211931.22
A26: Service | B26: Monthly cost | C26: Annual cost
A27: Cleaning | B27: 850 | C27: =B27*12 -> 10200
A28: Advertising | B28: 800 | C28: =B28*12 -> 9600
A29: Accounting services | B29: 550 | C29: =B29*12 -> 6600
A30: Quality control | B30: 400 | C30: =B30*12 -> 4800
A31: Taxes and fees | B31: 120 | C31: =B31*12 -> 1440
A32: Rent / lease | B32: 1350 | C32: =B32*12 -> 16200
A33: Vehicle leasing fees | B33: 900 | C33: =B33*12 -> 10800
A34: Maintenance, repair and upkeep | B34: 140 | C34: =B34*12 -> 1680
A35: Small tools and equipment | B35: 120 | C35: =B35*12 -> 1440
A36: Electricity consumption | B36: 120 | C36: =B36*12 -> 1440
A37: Heating energy consumption | B37: 180 | C37: =B37*12 -> 2160
A38: Water consumption | B38: 55 | C38: =B38*12 -> 660
... A49: Depreciation expense of fixed assets | B49: 685 | C49: =B49*12 -> 8220
A50: Total | C50: =SUM(C27:C49) -> 107040
A52: Equipment/licenses | B52: Units | C52: Price | D52: Total cost | E52: Annual cost | F52: Type | G52: Term
A53: Azure data center | B53: 1 | C53: 8000 | D53: =C53*B53 -> 8000 | E53: =D53 -> 8000 | F53: Rental
A54: Administrative equipment | B54: 3 | C54: 1000 | D54: =C54*B54 -> 3000 | E54: =D54/G54 -> 750 | F54: Depreciation | G54: 4
A55: Development equipment | B55: 6 | C55: 1400 | D55: =C55*B55 -> 8400 | E55: =D55/G55 -> 2100 | F55: Depreciation | G55: 4
A56: Laptops | B56: 5 | C56: 1500 | D56: =C56*B56 -> 7500 | E56: =D56/G56 -> 1875 | F56: Depreciation | G56: 4
A57: Development licenses | B57: 10 | C57: 200 | D57: =C57*B57 -> 2000 | E57: =D57 -> 2000 | F57: Rental
A58: Apple developer program annual fee | B58: 1 | C58: 99 | D58: =C58*B58 -> 99 | E58: =D58 -> 99 | F58: Rental
A59: Google play console registration | B59: 1 | C59: 25 | D59: =C59*B59 -> 25 | E59: =D59 -> 25 | F59: Rental
A60: Collaboration tools | B60: 14 | C60: 120 | D60: =C60*B60 -> 1680 | E60: =D60 -> 1680 | F60: Rental
A61: Total | D61: =SUM(D54:D60) -> 22704 | E61: =SUM(E53:E60) -> 16529
A63: Personnel | B63: Prod(%) | C63: Hours / year | D63: Productive hours per year (per person) | E63: Total productive hours
A64: General manager | B64: =C15 -> 0 | E64: =D64*B2 -> 0
A65: Project manager | B65: =C16 -> 0.65 | C65: 2008 | D65: =C65*B65 -> 1305.2 | E65: =D65*B3 -> 1305.2
A66: Service coordinator | B66: =C17 -> 0.5 | C66: 2008 | D66: =C66*B66 -> 1004 | E66: =D66*B4 -> 1004
A67: Systems analyst | B67: =C18 -> 0.8 | C67: 2008 | D67: =C67*B67 -> 1606.4 | E67: =D67*B5 -> 1606.4
A68: Technology consultant | B68: =C19 -> 0.85 | C68: 2008 | D68: =C68*B68 -> 1706.8 | E68: =D68*B6 -> 1706.8
A69: Software architect | B69: =C20 -> 0.75 | C69: 2008 | D69: =C69*B69 -> 1506 | E69: =D69*B7 -> 1506
A70: Senior developer | B70: =C21 -> 0.85 | C70: 2008 | D70: =C70*B70 -> 1706.8 | E70: =D70*B8 -> 3413.6
A71: Junior developer | B71: =C22 -> 0.7 | C71: 2008 | D71: =C71*B71 -> 1405.6 | E71: =D71*B9 -> 5622.4
A72: Sales representative | B72: =C23 -> 0 | E72: =D72*B10 -> 0
A73: TOTAL | E73: =SUM(E64:E72) -> 16164.4
A75: Indirect costs | B75: =E61+C50+F24 -> 335500.22
A76: Productive employees | B76: =SUMIFS(B2:B10,C15:C23,">0") -> 11
A77: Indirect costs per productive employee | B77: =IFERROR(B75/B76,"sin valor") -> 30500.02
A78: Indirect costs including profit | B78: =B77*(1+J5) -> 38125.025
A80: Personnel | B80: Direct cost / hour | C80: Hourly rate (with profit) | D80: Productive hours | E80: Revenue | F80: Hourly rate (without profit)
A81: General manager | B81: =IFERROR($D15/$D64,0) -> 0 | C81: =IFERROR(($D15+$B$78)/$D64,0) -> 0 | D81: =E64 -> 0 | E81: =D81*C81 -> 0 | F81: =IFERROR(($D15+$B$78)/$D64,0) -> 0
A82: Project manager | B82: =IFERROR($D16/$D65,0) -> 26.414044 | C82: =IFERROR(($D16+$B$78)/$D65,0) -> 55.624146 | D82: =E65 -> 1305.2 | E82: =D82*C82 -> 72600.635 | F82: =IFERROR(($D16+$B$77)/$D65,0) -> 49.782125
A83: Service coordinator | B83: =IFERROR($D17/$D66,0) -> 16.372799 | C83: =IFERROR(($D17+$B$78)/$D66,0) -> 54.345931 | D83: =E66 -> 1004 | E83: =D83*C83 -> 54563.315 | F83: =IFERROR(($D17+$B$77)/$D66,0) -> 46.751305
A84: Systems analyst | B84: =IFERROR($D18/$D67,0) -> 23.172703 | C84: =IFERROR(($D18+$B$78)/$D67,0) -> 46.905911 | D84: =E67 -> 1606.4 | E84: =D84*C84 -> 75349.655 | F84: =IFERROR(($D18+$B$77)/$D67,0) -> 42.159269
A85: Technology consultant | B85: =IFERROR($D19/$D68,0) -> 27.35075 | C85: =IFERROR(($D19+$B$78)/$D68,0) -> 49.687887 | D85: =E68 -> 1706.8 | E85: =D85*C85 -> 84807.285 | F85: =IFERROR(($D19+$B$77)/$D68,0) -> 45.220459
A86: Software architect | B86: =IFERROR($D20/$D69,0) -> 28.90172 | C86: =IFERROR(($D20+$B$78)/$D69,0) -> 54.217141 | D86: =E69 -> 1506 | E86: =D86*C86 -> 81651.015 | F86: =IFERROR(($D20+$B$77)/$D69,0) -> 49.154057
A87: Senior developer | B87: =IFERROR($D21/$D70,0) -> 25.976957 | C87: =IFERROR(($D21+$B$78)/$D70,0) -> 48.314094 | D87: =E70 -> 3413.6 | E87: =D87*C87 -> 164924.99 | F87: =IFERROR(($D21+$B$77)/$D70,0) -> 43.846666
A88: Junior developer | B88: =IFERROR($D22/$D71,0) -> 16.852881 | C88: =IFERROR(($D22+$B$78)/$D71,0) -> 43.976547 | D88: =E71 -> 5622.4 | E88: =D88*C88 -> 247253.74 | F88: =IFERROR(($D22+$B$77)/$D71,0) -> 38.551814
A89: Sales representative | B89: =IFERROR($D23/$D72,0) -> 0 | C89: =IFERROR(($D23+$B$78)/$D72,0) -> 0 | D89: =E72 -> 0 | E89: =D89*C89 -> 0 | F89: =IFERROR(($D23+$B$77)/$D72,0) -> 0
A90: TOTAL | D90: =SUM(D81:D89) -> 16164.4 | E90: =SUM(E81:E89) -> 781150.64

Sheet Costs_init
A1: Category 1: IrBoard development costs breakdown | L1: with proportional increase | N1: IrBoard costs
A2: I1 | B2: I2 | C2: I3 | D2: Description | E2: Resource | F2: Cuantity | G2: Units | H2: Price | I2: Subtotal | J2: Subtotal (2) | K2: Total | N2: Cat. Num | O2: Category | P2: Total
A3: 01 | D3: Project management | H3: =_xlfn.XLOOKUP(E3,$Q$20:$Q$25,$R$20:$R$25,"") | I3: =IFERROR(H3*F3,"") | K3: =SUM(J4:J19) -> 1493.4638 | L3: =IFERROR(I3+($P$10*F3),"") | N3: 01 | O3: IrBoard development costs breakdown | P3: =K74 -> 13026.517
B4: 001 | D4: Design project schedule | E4: Project manager | F4: 2 | G4: Hours | H4: =_xlfn.XLOOKUP(E4,$Q$20:$Q$25,$R$20:$R$25,"") -> 49.782125 | I4: =IFERROR(H4*F4,"") -> 99.564251 | J4: =I4 -> 99.564251 | L4: =IFERROR(I4+($P$10*F4),"") -> 122.72425 | N4: 02 | O4: Other | P4: =K81 -> 172.5
B5: 002 | D5: Generate budget | E5: Project manager | F5: 2 | G5: Hours | H5: =_xlfn.XLOOKUP(E5,$Q$20:$Q$25,$R$20:$R$25,"") -> 49.782125 | I5: =IFERROR(H5*F5,"") -> 99.564251 | J5: =I5 -> 99.564251 | L5: =IFERROR(I5+($P$10*F5),"") -> 122.72425 | N5: total | P5: =SUM(P3:P4) -> 13199.017
B6: 003 | D6: Periodic project management | H6: =_xlfn.XLOOKUP(E6,$Q$20:$Q$25,$R$20:$R$25,"") | I6: =IFERROR(H6*F6,"") | J6: =SUM(I7:I19) -> 1294.3353
C7: 01 | D7: Periodic project management 1 | E7: Project manager | F7: 2 | G7: Hours | H7: =_xlfn.XLOOKUP(E7,$Q$20:$Q$25,$R$20:$R$25,"") -> 49.782125 | I7: =IFERROR(H7*F7,"") -> 99.564251 | L7: =IFERROR(I7+($P$10*F7),"") -> 122.72425 | O7: Profit (25%) | P7: =0.25*(P3+P4) -> 3299.7543
C8: 02 | D8: Periodic project management 2 | E8: Project manager | F8: 2 | G8: Hours | H8: =_xlfn.XLOOKUP(E8,$Q$20:$Q$25,$R$20:$R$25,"") -> 49.782125 | I8: =IFERROR(H8*F8,"") -> 99.564251 | L8: =IFERROR(I8+($P$10*F8),"") -> 122.72425 | O8: amount to be increased on the first category | P8: =P5+P7-P3 -> 3472.2543
C9: 03 | D9: Periodic project management 3 | E9: Project manager | F9: 2 | G9: Hours | H9: =_xlfn.XLOOKUP(E9,$Q$20:$Q$25,$R$20:$R$25,"") -> 49.782125 | I9: =IFERROR(H9*F9,"") -> 99.564251 | L9: =IFERROR(I9+($P$10*F9),"") -> 122.72425 | O9: total hours | P9: =SUM(F4:F73) -> 300
C10: 04 | D10: Periodic project management 4 | E10: Project manager | F10: 2 | G10: Hours | H10: =_xlfn.XLOOKUP(E10,$Q$20:$Q$25,$R$20:$R$25,"") -> 49.782125 | I10: =IFERROR(H10*F10,"") -> 99.564251 | L10: =IFERROR(I10+($P$10*F10),"") -> 122.72425 | O10: Dilution increase per billable hour | P10: =ROUNDUP(P8/P9,2) -> 11.58
C11: 05 | D11: Periodic project management 5 | E11: Project manager | F11: 2 | G11: Hours | H11: =_xlfn.XLOOKUP(E11,$Q$20:$Q$25,$R$20:$R$25,"") -> 49.782125 | I11: =IFERROR(H11*F11,"") -> 99.564251 | L11: =IFERROR(I11+($P$10*F11),"") -> 122.72425 | O11: estimated client cost: | P11: =P5+P7 -> 16498.772
C12: 06 | D12: Periodic project management 6 | E12: Project manager | F12: 2 | G12: Hours | H12: =_xlfn.XLOOKUP(E12,$Q$20:$Q$25,$R$20:$R$25,"") -> 49.782125 | I12: =IFERROR(H12*F12,"") -> 99.564251 | L12: =IFERROR(I12+($P$10*F12),"") -> 122.72425
C13: 07 | D13: Periodic project management 7 | E13: Project manager | F13: 2 | G13: Hours | H13: =_xlfn.XLOOKUP(E13,$Q$20:$Q$25,$R$20:$R$25,"") -> 49.782125 | I13: =IFERROR(H13*F13,"") -> 99.564251 | L13: =IFERROR(I13+($P$10*F13),"") -> 122.72425
C14: 08 | D14: Periodic project management 8 | E14: Project manager | F14: 2 | G14: Hours | H14: =_xlfn.XLOOKUP(E14,$Q$20:$Q$25,$R$20:$R$25,"") -> 49.782125 | I14: =IFERROR(H14*F14,"") -> 99.564251 | L14: =IFERROR(I14+($P$10*F14),"") -> 122.72425
C15: 09 | D15: Periodic project management 9 | E15: Project manager | F15: 2 | G15: Hours | H15: =_xlfn.XLOOKUP(E15,$Q$20:$Q$25,$R$20:$R$25,"") -> 49.782125 | I15: =IFERROR(H15*F15,"") -> 99.564251 | L15: =IFERROR(I15+($P$10*F15),"") -> 122.72425
C16: 10 | D16: Periodic project management 10 | E16: Project manager | F16: 2 | G16: Hours | H16: =_xlfn.XLOOKUP(E16,$Q$20:$Q$25,$R$20:$R$25,"") -> 49.782125 | I16: =IFERROR(H16*F16,"") -> 99.564251 | L16: =IFERROR(I16+($P$10*F16),"") -> 122.72425
C17: 11 | D17: Periodic project management 11 | E17: Project manager | F17: 2 | G17: Hours | H17: =_xlfn.XLOOKUP(E17,$Q$20:$Q$25,$R$20:$R$25,"") -> 49.782125 | I17: =IFERROR(H17*F17,"") -> 99.564251 | L17: =IFERROR(I17+($P$10*F17),"") -> 122.72425
C18: 12 | D18: Periodic project management 12 | E18: Project manager | F18: 2 | G18: Hours | H18: =_xlfn.XLOOKUP(E18,$Q$20:$Q$25,$R$20:$R$25,"") -> 49.782125 | I18: =IFERROR(H18*F18,"") -> 99.564251 | L18: =IFERROR(I18+($P$10*F18),"") -> 122.72425
C19: 13 | D19: Periodic project management 13 | E19: Project manager | F19: 2 | G19: Hours | H19: =_xlfn.XLOOKUP(E19,$Q$20:$Q$25,$R$20:$R$25,"") -> 49.782125 | I19: =IFERROR(H19*F19,"") -> 99.564251 | L19: =IFERROR(I19+($P$10*F19),"") -> 122.72425 | Q19: Available resources | R19: Hourly rate (without profit)
A20: 02 | D20: Analysis/Software Requirements | H20: =_xlfn.XLOOKUP(E20,$Q$20:$Q$25,$R$20:$R$25,"") | I20: =IFERROR(H20*F20,"") | K20: =SUM(J21:J30) -> 2307.2124 | L20: =IFERROR(I20+($P$10*F20),"") | Q20: Project manager | R20: ='Company definition'!F82 -> 49.782125
B21: 001 | D21: Determine project scope | E21: System Analyst | F21: 1 | G21: Hours | H21: =_xlfn.XLOOKUP(E21,$Q$20:$Q$25,$R$20:$R$25,"") -> 42.159269 | I21: =IFERROR(H21*F21,"") -> 42.159269 | J21: =I21 -> 42.159269 | L21: =IFERROR(I21+($P$10*F21),"") -> 53.739269 | Q21: Technology consultant | R21: ='Company definition'!F85 -> 45.220459
B22: 002 | D22: Review Regulatory Standards | E22: Technology consultant | F22: 4 | G22: Hours | H22: =_xlfn.XLOOKUP(E22,$Q$20:$Q$25,$R$20:$R$25,"") -> 45.220459 | I22: =IFERROR(H22*F22,"") -> 180.88184 | J22: =I22 -> 180.88184 | L22: =IFERROR(I22+($P$10*F22),"") -> 227.20184 | Q22: System Analyst | R22: ='Company definition'!F84 -> 42.159269
B23: 003 | D23: Identify required Documentation | E23: System Analyst | F23: 2 | G23: Hours | H23: =_xlfn.XLOOKUP(E23,$Q$20:$Q$25,$R$20:$R$25,"") -> 42.159269 | I23: =IFERROR(H23*F23,"") -> 84.318538 | J23: =I23 -> 84.318538 | L23: =IFERROR(I23+($P$10*F23),"") -> 107.47854 | Q23: Software architect | R23: ='Company definition'!F86 -> 49.154057
B24: 004 | D24: Determine hand-ins for the project | E24: System Analyst | F24: 1 | G24: Hours | H24: =_xlfn.XLOOKUP(E24,$Q$20:$Q$25,$R$20:$R$25,"") -> 42.159269 | I24: =IFERROR(H24*F24,"") -> 42.159269 | J24: =I24 -> 42.159269 | L24: =IFERROR(I24+($P$10*F24),"") -> 53.739269 | Q24: Senior software engineer | R24: ='Company definition'!F87 -> 43.846666
B25: 005 | D25: Adapt project template to typst | E25: System Analyst | F25: 2 | G25: Hours | H25: =_xlfn.XLOOKUP(E25,$Q$20:$Q$25,$R$20:$R$25,"") -> 42.159269 | I25: =IFERROR(H25*F25,"") -> 84.318538 | J25: =I25 -> 84.318538 | L25: =IFERROR(I25+($P$10*F25),"") -> 107.47854 | Q25: Junior software engineer | R25: ='Company definition'!F88 -> 38.551814
B26: 006 | D26: Analyze existing systems | E26: Technology consultant | F26: 6 | G26: Hours | H26: =_xlfn.XLOOKUP(E26,$Q$20:$Q$25,$R$20:$R$25,"") -> 45.220459 | I26: =IFERROR(H26*F26,"") -> 271.32276 | J26: =I26 -> 271.32276 | L26: =IFERROR(I26+($P$10*F26),"") -> 340.80276
B27: 007 | D27: Draft preliminary software requirements | E27: System Analyst | F27: 22 | G27: Hours | H27: =_xlfn.XLOOKUP(E27,$Q$20:$Q$25,$R$20:$R$25,"") -> 42.159269 | I27: =IFERROR(H27*F27,"") -> 927.50392 | J27: =I27 -> 927.50392 | L27: =IFERROR(I27+($P$10*F27),"") -> 1182.2639
B28: 008 | D28: Model auxiliary diagrams | E28: System Analyst | F28: 6 | G28: Hours | H28: =_xlfn.XLOOKUP(E28,$Q$20:$Q$25,$R$20:$R$25,"") -> 42.159269 | I28: =IFERROR(H28*F28,"") -> 252.95562 | J28: =I28 -> 252.95562 | L28: =IFERROR(I28+($P$10*F28),"") -> 322.43562
B29: 009 | D29: Review software requirements | E29: System Analyst | F29: 2 | G29: Hours | H29: =_xlfn.XLOOKUP(E29,$Q$20:$Q$25,$R$20:$R$25,"") -> 42.159269 | I29: =IFERROR(H29*F29,"") -> 84.318538 | J29: =I29 -> 84.318538 | L29: =IFERROR(I29+($P$10*F29),"") -> 107.47854
B30: 010 | D30: Modify requirements with feedback | E30: System Analyst | F30: 8 | G30: Hours | H30: =_xlfn.XLOOKUP(E30,$Q$20:$Q$25,$R$20:$R$25,"") -> 42.159269 | I30: =IFERROR(H30*F30,"") -> 337.27415 | J30: =I30 -> 337.27415 | L30: =IFERROR(I30+($P$10*F30),"") -> 429.91415
A31: 03 | D31: Design | H31: =_xlfn.XLOOKUP(E31,$Q$20:$Q$25,$R$20:$R$25,"") | I31: =IFERROR(H31*F31,"") | K31: =SUM(J32:J38) -> 2273.3693 | L31: =IFERROR(I31+($P$10*F31),"")
B32: 001 | D32: Design architecture | E32: Software architect | F32: 10 | G32: Hours | H32: =_xlfn.XLOOKUP(E32,$Q$20:$Q$25,$R$20:$R$25,"") -> 49.154057 | I32: =IFERROR(H32*F32,"") -> 491.54057 | J32: =I32 -> 491.54057 | L32: =IFERROR(I32+($P$10*F32),"") -> 607.34057
B33: 002 | D33: Design brand identity | E33: Junior software engineer | F33: 3 | G33: Hours | H33: =_xlfn.XLOOKUP(E33,$Q$20:$Q$25,$R$20:$R$25,"") -> 38.551814 | I33: =IFERROR(H33*F33,"") -> 115.65544 | J33: =I33 -> 115.65544 | L33: =IFERROR(I33+($P$10*F33),"") -> 150.39544
B34: 003 | D34: Design project management | E34: Senior software engineer | F34: 8 | G34: Hours | H34: =_xlfn.XLOOKUP(E34,$Q$20:$Q$25,$R$20:$R$25,"") -> 43.846666 | I34: =IFERROR(H34*F34,"") -> 350.77333 | J34: =I34 -> 350.77333 | L34: =IFERROR(I34+($P$10*F34),"") -> 443.41333
B35: 004 | D35: Design stakeholder management | E35: Senior software engineer | F35: 4 | G35: Hours | H35: =_xlfn.XLOOKUP(E35,$Q$20:$Q$25,$R$20:$R$25,"") -> 43.846666 | I35: =IFERROR(H35*F35,"") -> 175.38667 | J35: =I35 -> 175.38667 | L35: =IFERROR(I35+($P$10*F35),"") -> 221.70667
B36: 005 | D36: Design requirement management | E36: Senior software engineer | F36: 6 | G36: Hours | H36: =_xlfn.XLOOKUP(E36,$Q$20:$Q$25,$R$20:$R$25,"") -> 43.846666 | I36: =IFERROR(H36*F36,"") -> 263.08 | J36: =I36 -> 263.08 | L36: =IFERROR(I36+($P$10*F36),"") -> 332.56
B37: 006 | D37: Design user management | E37: Senior software engineer | F37: 10 | G37: Hours | H37: =_xlfn.XLOOKUP(E37,$Q$20:$Q$25,$R$20:$R$25,"") -> 43.846666 | I37: =IFERROR(H37*F37,"") -> 438.46666 | J37: =I37 -> 438.46666 | L37: =IFERROR(I37+($P$10*F37),"") -> 554.26666
B38: 007 | D38: Design document management | E38: Senior software engineer | F38: 10 | G38: Hours | H38: =_xlfn.XLOOKUP(E38,$Q$20:$Q$25,$R$20:$R$25,"") -> 43.846666 | I38: =IFERROR(H38*F38,"") -> 438.46666 | J38: =I38 -> 438.46666 | L38: =IFERROR(I38+($P$10*F38),"") -> 554.26666
A39: 04 | D39: Set up SonarQube for Quality Assurance | E39: Senior software engineer | F39: 3 | G39: Hours | H39: =_xlfn.XLOOKUP(E39,$Q$20:$Q$25,$R$20:$R$25,"") -> 43.846666 | I39: =IFERROR(H39*F39,"") -> 131.54 | J39: =SUM(I39) -> 131.54 | K39: =SUM(J39) -> 131.54 | L39: =IFERROR(I39+($P$10*F39),"") -> 166.28
A40: 05 | D40: Development | H40: =_xlfn.XLOOKUP(E40,$Q$20:$Q$25,$R$20:$R$25,"") | I40: =IFERROR(H40*F40,"") | K40: =SUM(J41:J50) -> 4386.8988 | L40: =IFERROR(I40+($P$10*F40),"")
B41: 001 | D41: Set up architecture | E41: Software architect | F41: 4 | G41: Hours | H41: =_xlfn.XLOOKUP(E41,$Q$20:$Q$25,$R$20:$R$25,"") -> 49.154057 | I41: =IFERROR(H41*F41,"") -> 196.61623 | J41: =I41 -> 196.61623 | L41: =IFERROR(I41+($P$10*F41),"") -> 242.93623
B42: 002 | D42: Set up development enviroment | E42: Software architect | F42: 3 | G42: Hours | H42: =_xlfn.XLOOKUP(E42,$Q$20:$Q$25,$R$20:$R$25,"") -> 49.154057 | I42: =IFERROR(H42*F42,"") -> 147.46217 | J42: =I42 -> 147.46217 | L42: =IFERROR(I42+($P$10*F42),"") -> 182.20217
B43: 003 | D43: Develop code | H43: =_xlfn.XLOOKUP(E43,$Q$20:$Q$25,$R$20:$R$25,"") | I43: =IFERROR(H43*F43,"") | J43: =SUM(I44:I50) -> 4042.8204 | L43: =IFERROR(I43+($P$10*F43),"")
C44: 01 | D44: Develop project management module | E44: Junior software engineer | F44: 22 | G44: Hours | H44: =_xlfn.XLOOKUP(E44,$Q$20:$Q$25,$R$20:$R$25,"") -> 38.551814 | I44: =IFERROR(H44*F44,"") -> 848.13991 | L44: =IFERROR(I44+($P$10*F44),"") -> 1102.8999
C45: 02 | D45: Develop stakeholder management module | E45: Junior software engineer | F45: 10 | G45: Hours | H45: =_xlfn.XLOOKUP(E45,$Q$20:$Q$25,$R$20:$R$25,"") -> 38.551814 | I45: =IFERROR(H45*F45,"") -> 385.51814 | L45: =IFERROR(I45+($P$10*F45),"") -> 501.31814
C46: 03 | D46: Develop requirement management module | E46: Senior software engineer | F46: 25 | G46: Hours | H46: =_xlfn.XLOOKUP(E46,$Q$20:$Q$25,$R$20:$R$25,"") -> 43.846666 | I46: =IFERROR(H46*F46,"") -> 1096.1667 | L46: =IFERROR(I46+($P$10*F46),"") -> 1385.6667
C47: 04 | D47: Develop user management module | E47: Junior software engineer | F47: 6 | G47: Hours | H47: =_xlfn.XLOOKUP(E47,$Q$20:$Q$25,$R$20:$R$25,"") -> 38.551814 | I47: =IFERROR(H47*F47,"") -> 231.31089 | L47: =IFERROR(I47+($P$10*F47),"") -> 300.79089
C48: 05 | D48: Develop document management | E48: Senior software engineer | F48: 15 | G48: Hours | H48: =_xlfn.XLOOKUP(E48,$Q$20:$Q$25,$R$20:$R$25,"") -> 43.846666 | I48: =IFERROR(H48*F48,"") -> 657.69999 | L48: =IFERROR(I48+($P$10*F48),"") -> 831.39999
C49: 06 | D49: Develop modifying concurrency system | E49: Senior software engineer | F49: 10 | G49: Hours | H49: =_xlfn.XLOOKUP(E49,$Q$20:$Q$25,$R$20:$R$25,"") -> 43.846666 | I49: =IFERROR(H49*F49,"") -> 438.46666 | L49: =IFERROR(I49+($P$10*F49),"") -> 554.26666
C50: 07 | D50: Develop search and filtering | E50: Junior software engineer | F50: 10 | G50: Hours | H50: =_xlfn.XLOOKUP(E50,$Q$20:$Q$25,$R$20:$R$25,"") -> 38.551814 | I50: =IFERROR(H50*F50,"") -> 385.51814 | L50: =IFERROR(I50+($P$10*F50),"") -> 501.31814
A51: 06 | D51: Testing | H51: =_xlfn.XLOOKUP(E51,$Q$20:$Q$25,$R$20:$R$25,"") | I51: =IFERROR(H51*F51,"") | K51: =SUM(J52:J60) -> 1051.4887 | L51: =IFERROR(I51+($P$10*F51),"")
B52: 001 | D52: Test project management module | E52: Junior software engineer | F52: 4 | G52: Hours | H52: =_xlfn.XLOOKUP(E52,$Q$20:$Q$25,$R$20:$R$25,"") -> 38.551814 | I52: =IFERROR(H52*F52,"") -> 154.20726 | J52: =I52 -> 154.20726 | L52: =IFERROR(I52+($P$10*F52),"") -> 200.52726
B53: 002 | D53: Test stakeholder management module | E53: Junior software engineer | F53: 3 | G53: Hours | H53: =_xlfn.XLOOKUP(E53,$Q$20:$Q$25,$R$20:$R$25,"") -> 38.551814 | I53: =IFERROR(H53*F53,"") -> 115.65544 | J53: =I53 -> 115.65544 | L53: =IFERROR(I53+($P$10*F53),"") -> 150.39544
B54: 003 | D54: Test requirement management module | E54: Junior software engineer | F54: 5 | G54: Hours | H54: =_xlfn.XLOOKUP(E54,$Q$20:$Q$25,$R$20:$R$25,"") -> 38.551814 | I54: =IFERROR(H54*F54,"") -> 192.75907 | J54: =I54 -> 192.75907 | L54: =IFERROR(I54+($P$10*F54),"") -> 250.65907
B55: 004 | D55: Test user management module | E55: Junior software engineer | F55: 3 | G55: Hours | H55: =_xlfn.XLOOKUP(E55,$Q$20:$Q$25,$R$20:$R$25,"") -> 38.551814 | I55: =IFERROR(H55*F55,"") -> 115.65544 | J55: =I55 -> 115.65544 | L55: =IFERROR(I55+($P$10*F55),"") -> 150.39544
B56: 005 | D56: Test document management | E56: Junior software engineer | F56: 3 | G56: Hours | H56: =_xlfn.XLOOKUP(E56,$Q$20:$Q$25,$R$20:$R$25,"") -> 38.551814 | I56: =IFERROR(H56*F56,"") -> 115.65544 | J56: =I56 -> 115.65544 | L56: =IFERROR(I56+($P$10*F56),"") -> 150.39544
B57: 006 | D57: Test modifying concurrency system | E57: Junior software engineer | F57: 2 | G57: Hours | H57: =_xlfn.XLOOKUP(E57,$Q$20:$Q$25,$R$20:$R$25,"") -> 38.551814 | I57: =IFERROR(H57*F57,"") -> 77.103628 | J57: =I57 -> 77.103628 | L57: =IFERROR(I57+($P$10*F57),"") -> 100.26363
B58: 007 | D58: Test search and filtering | E58: Junior software engineer | F58: 3 | G58: Hours | H58: =_xlfn.XLOOKUP(E58,$Q$20:$Q$25,$R$20:$R$25,"") -> 38.551814 | I58: =IFERROR(H58*F58,"") -> 115.65544 | J58: =I58 -> 115.65544 | L58: =IFERROR(I58+($P$10*F58),"") -> 150.39544
B59: 008 | D59: Usability and accesibility testing | E59: Junior software engineer | F59: 2 | G59: Hours | H59: =_xlfn.XLOOKUP(E59,$Q$20:$Q$25,$R$20:$R$25,"") -> 38.551814 | I59: =IFERROR(H59*F59,"") -> 77.103628 | J59: =I59 -> 77.103628 | L59: =IFERROR(I59+($P$10*F59),"") -> 100.26363
B60: 009 | D60: Load testing | E60: Senior software engineer | F60: 2 | G60: Hours | H60: =_xlfn.XLOOKUP(E60,$Q$20:$Q$25,$R$20:$R$25,"") -> 43.846666 | I60: =IFERROR(H60*F60,"") -> 87.693333 | J60: =I60 -> 87.693333 | L60: =IFERROR(I60+($P$10*F60),"") -> 110.85333
A61: 07 | D61: Documentation | H61: =_xlfn.XLOOKUP(E61,$Q$20:$Q$25,$R$20:$R$25,"") | I61: =IFERROR(H61*F61,"") | K61: =SUM(J62:J73) -> 1382.5443 | L61: =IFERROR(I61+($P$10*F61),"")
B62: 001 | D62: Document declaration of originality, abstract and keywords | E62: Project manager | F62: 1 | G62: Hours | H62: =_xlfn.XLOOKUP(E62,$Q$20:$Q$25,$R$20:$R$25,"") -> 49.782125 | I62: =IFERROR(H62*F62,"") -> 49.782125 | J62: =I62 -> 49.782125 | L62: =IFERROR(I62+($P$10*F62),"") -> 61.362125
B63: 002 | D63: Document introduction | E63: Project manager | F63: 1 | G63: Hours | H63: =_xlfn.XLOOKUP(E63,$Q$20:$Q$25,$R$20:$R$25,"") -> 49.782125 | I63: =IFERROR(H63*F63,"") -> 49.782125 | J63: =I63 -> 49.782125 | L63: =IFERROR(I63+($P$10*F63),"") -> 61.362125
B64: 003 | D64: Document theoretical background | E64: Technology consultant | F64: 1 | G64: Hours | H64: =_xlfn.XLOOKUP(E64,$Q$20:$Q$25,$R$20:$R$25,"") -> 45.220459 | I64: =IFERROR(H64*F64,"") -> 45.220459 | J64: =I64 -> 45.220459 | L64: =IFERROR(I64+($P$10*F64),"") -> 56.800459
B65: 004 | D65: Document feasibility study and alternative analysis | E65: Technology consultant | F65: 2 | G65: Hours | H65: =_xlfn.XLOOKUP(E65,$Q$20:$Q$25,$R$20:$R$25,"") -> 45.220459 | I65: =IFERROR(H65*F65,"") -> 90.440919 | J65: =I65 -> 90.440919 | L65: =IFERROR(I65+($P$10*F65),"") -> 113.60092
B66: 005 | D66: Document Initial project planning and management | E66: Project manager | F66: 2 | G66: Hours | H66: =_xlfn.XLOOKUP(E66,$Q$20:$Q$25,$R$20:$R$25,"") -> 49.782125 | I66: =IFERROR(H66*F66,"") -> 99.564251 | J66: =I66 -> 99.564251 | L66: =IFERROR(I66+($P$10*F66),"") -> 122.72425
B67: 006 | D67: Document system analysis | E67: System Analyst | F67: 3 | G67: Hours | H67: =_xlfn.XLOOKUP(E67,$Q$20:$Q$25,$R$20:$R$25,"") -> 42.159269 | I67: =IFERROR(H67*F67,"") -> 126.47781 | J67: =I67 -> 126.47781 | L67: =IFERROR(I67+($P$10*F67),"") -> 161.21781
B68: 007 | D68: Document system design | E68: Software architect | F68: 5 | G68: Hours | H68: =_xlfn.XLOOKUP(E68,$Q$20:$Q$25,$R$20:$R$25,"") -> 49.154057 | I68: =IFERROR(H68*F68,"") -> 245.77029 | J68: =I68 -> 245.77029 | L68: =IFERROR(I68+($P$10*F68),"") -> 303.67029
B69: 008 | D69: Document system implementation | E69: Senior software engineer | F69: 5 | G69: Hours | H69: =_xlfn.XLOOKUP(E69,$Q$20:$Q$25,$R$20:$R$25,"") -> 43.846666 | I69: =IFERROR(H69*F69,"") -> 219.23333 | J69: =I69 -> 219.23333 | L69: =IFERROR(I69+($P$10*F69),"") -> 277.13333
B70: 009 | D70: Document test plan execution | E70: Senior software engineer | F70: 2 | G70: Hours | H70: =_xlfn.XLOOKUP(E70,$Q$20:$Q$25,$R$20:$R$25,"") -> 43.846666 | I70: =IFERROR(H70*F70,"") -> 87.693333 | J70: =I70 -> 87.693333 | L70: =IFERROR(I70+($P$10*F70),"") -> 110.85333
B71: 010 | D71: Document system manuals | E71: Senior software engineer | F71: 5 | G71: Hours | H71: =_xlfn.XLOOKUP(E71,$Q$20:$Q$25,$R$20:$R$25,"") -> 43.846666 | I71: =IFERROR(H71*F71,"") -> 219.23333 | J71: =I71 -> 219.23333 | L71: =IFERROR(I71+($P$10*F71),"") -> 277.13333
B72: 011 | D72: Document final project closure | E72: Project manager | F72: 2 | G72: Hours | H72: =_xlfn.XLOOKUP(E72,$Q$20:$Q$25,$R$20:$R$25,"") -> 49.782125 | I72: =IFERROR(H72*F72,"") -> 99.564251 | J72: =I72 -> 99.564251 | L72: =IFERROR(I72+($P$10*F72),"") -> 122.72425
B73: 012 | D73: Document conclusions and future work | E73: Project manager | F73: 1 | G73: Hours | H73: =_xlfn.XLOOKUP(E73,$Q$20:$Q$25,$R$20:$R$25,"") -> 49.782125 | I73: =IFERROR(H73*F73,"") -> 49.782125 | J73: =I73 -> 49.782125 | L73: =IFERROR(I73+($P$10*F73),"") -> 61.362125
A74: Total | K74: =SUM(K3:K73) -> 13026.517 | L74: =SUM(L3:L73) -> 16500.517
A76: Category 2: Other
A77: I1 | B77: I2 | C77: I3 | D77: Description | E77: Resource | F77: Cuantity | G77: Units | H77: Price | I77: Subtotal | J77: Subtotal (2) | K77: Total
A78: 01 | D78: Travel and transportation expenses | J78: =SUM(I79:I80) -> 172.5 | K78: =J78 -> 172.5
B79: 001 | D79: Travel to client facilities (deployment/support) | E79: - | F79: 150 | G79: km | H79: 0.35 | I79: =H79*F79 -> 52.5
B80: 002 | D80: Meals/daily allowance | E80: - | F80: 6 | G80: meals | H80: 20 | I80: =H80*F80 -> 120
A81: Total | K81: =SUM(K78:K80) -> 172.5

Sheet Client_init
A1: Detailed client budget | G1: Simplified client budget
A2: I1 | B2: I2 | C2: Description | D2: Cost | E2: Total | G2: Cat. Num | H2: Category | I2: Total
A3: 01 | C3: Project management | E3: =SUM(D4:D6) -> 1840.8638 | G3: 01 | H3: IrBoard development costs breakdown | I3: =E54 -> 16500.517
B4: 001 | C4: Design project schedule | D4: =Costs_init!L4 -> 122.72425 | G4: total | I4: =SUM(I3) -> 16500.517
B5: 002 | C5: Generate budget | D5: =Costs_init!L5 -> 122.72425
B6: 003 | C6: Periodic project management | D6: =SUM(Costs_init!L7:L19) -> 1595.4153
A7: 02 | C7: Analysis/Software Requirements | E7: =SUM(D8:D17) -> 2932.5324
B8: 001 | C8: Determine project scope | D8: =Costs_init!L21 -> 53.739269
B9: 002 | C9: Review Regulatory Standards | D9: =Costs_init!L22 -> 227.20184
B10: 003 | C10: Identify required Documentation | D10: =Costs_init!L23 -> 107.47854
B11: 004 | C11: Determine hand-ins for the project | D11: =Costs_init!L24 -> 53.739269
B12: 005 | C12: Adapt project template to typst | D12: =Costs_init!L25 -> 107.47854
B13: 006 | C13: Analyze existing systems | D13: =Costs_init!L26 -> 340.80276
B14: 007 | C14: Draft preliminary software requirements | D14: =Costs_init!L27 -> 1182.2639
B15: 008 | C15: Model auxiliary diagrams | D15: =Costs_init!L28 -> 322.43562
B16: 009 | C16: Review software requirements | D16: =Costs_init!L29 -> 107.47854
B17: 010 | C17: Modify requirements with feedback | D17: =Costs_init!L30 -> 429.91415
A18: 03 | C18: Design | D18: =Costs_init!L31 | E18: =SUM(D19:D25) -> 2863.9493
B19: 001 | C19: Design architecture | D19: =Costs_init!L32 -> 607.34057
B20: 002 | C20: Design brand identity | D20: =Costs_init!L33 -> 150.39544
B21: 003 | C21: Design project management | D21: =Costs_init!L34 -> 443.41333
B22: 004 | C22: Design stakeholder management | D22: =Costs_init!L35 -> 221.70667
B23: 005 | C23: Design requirement management | D23: =Costs_init!L36 -> 332.56
B24: 006 | C24: Design user management | D24: =Costs_init!L37 -> 554.26666
B25: 007 | C25: Design document management | D25: =Costs_init!L38 -> 554.26666
A26: 04 | C26: Set up SonarQube for Quality Assurance | D26: =Costs_init!L39 -> 166.28 | E26: =D26 -> 166.28
A27: 05 | C27: Development | D27: =Costs_init!L40 | E27: =SUM(D28:D30) -> 5602.7988
B28: 001 | C28: Set up architecture | D28: =Costs_init!L41 -> 242.93623
B29: 002 | C29: Set up development enviroment | D29: =Costs_init!L42 -> 182.20217
B30: 003 | C30: Develop code | D30: =SUM(Costs_init!L44:L50) -> 5177.6604
A31: 06 | C31: Testing | E31: =SUM(D32:D40) -> 1364.1487
B32: 001 | C32: Test project management module | D32: =Costs_init!L52 -> 200.52726
B33: 002 | C33: Test stakeholder management module | D33: =Costs_init!L53 -> 150.39544
B34: 003 | C34: Test requirement management module | D34: =Costs_init!L54 -> 250.65907
B35: 004 | C35: Test user management module | D35: =Costs_init!L55 -> 150.39544
B36: 005 | C36: Test document management | D36: =Costs_init!L56 -> 150.39544
B37: 006 | C37: Test modifying concurrency system | D37: =Costs_init!L57 -> 100.26363
B38: 007 | C38: Test search and filtering | D38: =Costs_init!L58 -> 150.39544
B39: 008 | C39: Usability and accesibility testing | D39: =Costs_init!L59 -> 100.26363
B40: 009 | C40: Load testing | D40: =Costs_init!L60 -> 110.85333
A41: 07 | C41: Documentation | D41: =Costs_init!L61 | E41: =SUM(D42:D53) -> 1729.9443
B42: 001 | C42: Document declaration of originality, abstract and keywords | D42: =Costs_init!L62 -> 61.362125
B43: 002 | C43: Document introduction | D43: =Costs_init!L63 -> 61.362125
B44: 003 | C44: Document theoretical background | D44: =Costs_init!L64 -> 56.800459
B45: 004 | C45: Document feasibility study and alternative analysis | D45: =Costs_init!L65 -> 113.60092
B46: 005 | C46: Document Initial project planning and management | D46: =Costs_init!L66 -> 122.72425
B47: 006 | C47: Document system analysis | D47: =Costs_init!L67 -> 161.21781
B48: 007 | C48: Document system design | D48: =Costs_init!L68 -> 303.67029
B49: 008 | C49: Document system implementation | D49: =Costs_init!L69 -> 277.13333
B50: 009 | C50: Document test plan execution | D50: =Costs_init!L70 -> 110.85333
B51: 010 | C51: Document system manuals | D51: =Costs_init!L71 -> 277.13333
B52: 011 | C52: Document final project closure | D52: =Costs_init!L72 -> 122.72425
B53: 012 | C53: Document conclusions and future work | D53: =Costs_init!L73 -> 61.362125
A54: Total | E54: =SUM(E3:E53) -> 16500.517

Sheet Costs_final
A1: Category 1: IrBoard development costs breakdown | N1: IrBoard costs
A2: I1 | B2: I2 | C2: I3 | D2: Description | E2: Resource | F2: Cuantity | G2: Units | H2: Price | I2: Subtotal | J2: Subtotal (2) | K2: Total | L2: deviation | N2: Cat. Num | O2: Category | P2: Total | Q2: deviation from original
A3: 01 | D3: Project management | H3: =_xlfn.XLOOKUP(E3,$Q$20:$Q$25,$R$20:$R$25,"") | I3: =IFERROR(H3*F3,"") | K3: =SUM(J4:J19) -> 1194.771 | L3: =((K3-Costs_init!K3)/Costs_init!K3) -> -0.2 | N3: 01 | O3: IrBoard development costs breakdown | P3: =K74 -> 13383.613 | Q3: =((P3-Costs_init!P3)/Costs_init!P3) -> 0.027412946
B4: 001 | D4: Design project schedule | E4: Project manager | F4: 2 | G4: Hours | H4: =_xlfn.XLOOKUP(E4,$Q$20:$Q$25,$R$20:$R$25,"") -> 49.782125 | I4: =IFERROR(H4*F4,"") -> 99.564251 | J4: =I4 -> 99.564251 | L4: =((J4-Costs_init!J4)/Costs_init!J4) -> 0 | N4: 02 | O4: Other | P4: =K81 -> 172.5 | Q4: =((P4-Costs_init!P4)/Costs_init!P4) -> 0
B5: 002 | D5: Generate budget | E5: Project manager | F5: 2 | G5: Hours | H5: =_xlfn.XLOOKUP(E5,$Q$20:$Q$25,$R$20:$R$25,"") -> 49.782125 | I5: =IFERROR(H5*F5,"") -> 99.564251 | J5: =I5 -> 99.564251 | L5: =((J5-Costs_init!J5)/Costs_init!J5) -> 0 | N5: total | P5: =SUM(P3:P4) -> 13556.113 | Q5: =((P5-Costs_init!P5)/Costs_init!P5) -> 0.027054682
B6: 003 | D6: Periodic project management | H6: =_xlfn.XLOOKUP(E6,$Q$20:$Q$25,$R$20:$R$25,"") | I6: =IFERROR(H6*F6,"") | J6: =SUM(I7:I19) -> 995.64251 | L6: =((J6-Costs_init!J6)/Costs_init!J6) -> -0.23076923
C7: 01 | D7: Periodic project management 1 | E7: Project manager | F7: 1 | G7: Hours | H7: =_xlfn.XLOOKUP(E7,$Q$20:$Q$25,$R$20:$R$25,"") -> 49.782125 | I7: =IFERROR(H7*F7,"") -> 49.782125 | L7: =((I7-Costs_init!I7)/Costs_init!I7) -> -0.5 | O7: Actual profit | P7: =Client_init!I4-Costs_final!P5 -> 2944.4048
C8: 02 | D8: Periodic project management 2 | E8: Project manager | F8: 2 | G8: Hours | H8: =_xlfn.XLOOKUP(E8,$Q$20:$Q$25,$R$20:$R$25,"") -> 49.782125 | I8: =IFERROR(H8*F8,"") -> 99.564251 | L8: =((I8-Costs_init!I8)/Costs_init!I8) -> 0 | O8: Profit deviation | P8: =((P7-Costs_init!P7)/Costs_init!P7) -> -0.1076897
C9: 03 | D9: Periodic project management 3 | E9: Project manager | F9: 1 | G9: Hours | H9: =_xlfn.XLOOKUP(E9,$Q$20:$Q$25,$R$20:$R$25,"") -> 49.782125 | I9: =IFERROR(H9*F9,"") -> 49.782125 | L9: =((I9-Costs_init!I9)/Costs_init!I9) -> -0.5 | P9: =(0.21)*(P3+P4) -> 2846.7836
C10: 04 | D10: Periodic project management 4 | E10: Project manager | F10: 2 | G10: Hours | H10: =_xlfn.XLOOKUP(E10,$Q$20:$Q$25,$R$20:$R$25,"") -> 49.782125 | I10: =IFERROR(H10*F10,"") -> 99.564251 | L10: =((I10-Costs_init!I10)/Costs_init!I10) -> 0 | P10: =P5+P9 -> 16402.896
C11: 05 | D11: Periodic project management 5 | E11: Project manager | F11: 1 | G11: Hours | H11: =_xlfn.XLOOKUP(E11,$Q$20:$Q$25,$R$20:$R$25,"") -> 49.782125 | I11: =IFERROR(H11*F11,"") -> 49.782125 | L11: =((I11-Costs_init!I11)/Costs_init!I11) -> -0.5
C12: 06 | D12: Periodic project management 6 | E12: Project manager | F12: 1 | G12: Hours | H12: =_xlfn.XLOOKUP(E12,$Q$20:$Q$25,$R$20:$R$25,"") -> 49.782125 | I12: =IFERROR(H12*F12,"") -> 49.782125 | L12: =((I12-Costs_init!I12)/Costs_init!I12) -> -0.5
C13: 07 | D13: Periodic project management 7 | E13: Project manager | F13: 2 | G13: Hours | H13: =_xlfn.XLOOKUP(E13,$Q$20:$Q$25,$R$20:$R$25,"") -> 49.782125 | I13: =IFERROR(H13*F13,"") -> 99.564251 | L13: =((I13-Costs_init!I13)/Costs_init!I13) -> 0
C14: 08 | D14: Periodic project management 8 | E14: Project manager | F14: 2 | G14: Hours | H14: =_xlfn.XLOOKUP(E14,$Q$20:$Q$25,$R$20:$R$25,"") -> 49.782125 | I14: =IFERROR(H14*F14,"") -> 99.564251 | L14: =((I14-Costs_init!I14)/Costs_init!I14) -> 0
C15: 09 | D15: Periodic project management 9 | E15: Project manager | F15: 2 | G15: Hours | H15: =_xlfn.XLOOKUP(E15,$Q$20:$Q$25,$R$20:$R$25,"") -> 49.782125 | I15: =IFERROR(H15*F15,"") -> 99.564251 | L15: =((I15-Costs_init!I15)/Costs_init!I15) -> 0
C16: 10 | D16: Periodic project management 10 | E16: Project manager | F16: 2 | G16: Hours | H16: =_xlfn.XLOOKUP(E16,$Q$20:$Q$25,$R$20:$R$25,"") -> 49.782125 | I16: =IFERROR(H16*F16,"") -> 99.564251 | L16: =((I16-Costs_init!I16)/Costs_init!I16) -> 0
C17: 11 | D17: Periodic project management 11 | E17: Project manager | F17: 1 | G17: Hours | H17: =_xlfn.XLOOKUP(E17,$Q$20:$Q$25,$R$20:$R$25,"") -> 49.782125 | I17: =IFERROR(H17*F17,"") -> 49.782125 | L17: =((I17-Costs_init!I17)/Costs_init!I17) -> -0.5
C18: 12 | D18: Periodic project management 12 | E18: Project manager | F18: 1 | G18: Hours | H18: =_xlfn.XLOOKUP(E18,$Q$20:$Q$25,$R$20:$R$25,"") -> 49.782125 | I18: =IFERROR(H18*F18,"") -> 49.782125 | L18: =((I18-Costs_init!I18)/Costs_init!I18) -> -0.5
C19: 13 | D19: Periodic project management 13 | E19: Project manager | F19: 2 | G19: Hours | H19: =_xlfn.XLOOKUP(E19,$Q$20:$Q$25,$R$20:$R$25,"") -> 49.782125 | I19: =IFERROR(H19*F19,"") -> 99.564251 | L19: =((I19-Costs_init!I19)/Costs_init!I19) -> 0 | Q19: Available resources | R19: Hourly rate (without profit)
A20: 02 | D20: Analysis/Software Requirements | H20: =_xlfn.XLOOKUP(E20,$Q$20:$Q$25,$R$20:$R$25,"") | I20: =IFERROR(H20*F20,"") | K20: =SUM(J21:J30) -> 2433.6902 | L20: =((K20-Costs_init!K20)/Costs_init!K20) -> 0.054818449 | Q20: Project manager | R20: ='Company definition'!F82 -> 49.782125
B21: 001 | D21: Determine project scope | E21: System Analyst | F21: 1 | G21: Hours | H21: =_xlfn.XLOOKUP(E21,$Q$20:$Q$25,$R$20:$R$25,"") -> 42.159269 | I21: =IFERROR(H21*F21,"") -> 42.159269 | J21: =I21 -> 42.159269 | L21: =((J21-Costs_init!J21)/Costs_init!J21) -> 0 | Q21: Technology consultant | R21: ='Company definition'!F85 -> 45.220459
B22: 002 | D22: Review Regulatory Standards | E22: Technology consultant | F22: 4 | G22: Hours | H22: =_xlfn.XLOOKUP(E22,$Q$20:$Q$25,$R$20:$R$25,"") -> 45.220459 | I22: =IFERROR(H22*F22,"") -> 180.88184 | J22: =I22 -> 180.88184 | L22: =((J22-Costs_init!J22)/Costs_init!J22) -> 0 | Q22: System Analyst | R22: ='Company definition'!F84 -> 42.159269
B23: 003 | D23: Identify required Documentation | E23: System Analyst | F23: 1 | G23: Hours | H23: =_xlfn.XLOOKUP(E23,$Q$20:$Q$25,$R$20:$R$25,"") -> 42.159269 | I23: =IFERROR(H23*F23,"") -> 42.159269 | J23: =I23 -> 42.159269 | L23: =((J23-Costs_init!J23)/Costs_init!J23) -> -0.5 | Q23: Software architect | R23: ='Company definition'!F86 -> 49.154057
B24: 004 | D24: Determine hand-ins for the project | E24: System Analyst | F24: 1 | G24: Hours | H24: =_xlfn.XLOOKUP(E24,$Q$20:$Q$25,$R$20:$R$25,"") -> 42.159269 | I24: =IFERROR(H24*F24,"") -> 42.159269 | J24: =I24 -> 42.159269 | L24: =((J24-Costs_init!J24)/Costs_init!J24) -> 0 | Q24: Senior software engineer | R24: ='Company definition'!F87 -> 43.846666
B25: 005 | D25: Adapt project template to typst | E25: System Analyst | F25: 2 | G25: Hours | H25: =_xlfn.XLOOKUP(E25,$Q$20:$Q$25,$R$20:$R$25,"") -> 42.159269 | I25: =IFERROR(H25*F25,"") -> 84.318538 | J25: =I25 -> 84.318538 | L25: =((J25-Costs_init!J25)/Costs_init!J25) -> 0 | Q25: Junior software engineer | R25: ='Company definition'!F88 -> 38.551814
B26: 006 | D26: Analyze existing systems | E26: Technology consultant | F26: 6 | G26: Hours | H26: =_xlfn.XLOOKUP(E26,$Q$20:$Q$25,$R$20:$R$25,"") -> 45.220459 | I26: =IFERROR(H26*F26,"") -> 271.32276 | J26: =I26 -> 271.32276 | L26: =((J26-Costs_init!J26)/Costs_init!J26) -> 0
B27: 007 | D27: Draft preliminary software requirements | E27: System Analyst | F27: 22 | G27: Hours | H27: =_xlfn.XLOOKUP(E27,$Q$20:$Q$25,$R$20:$R$25,"") -> 42.159269 | I27: =IFERROR(H27*F27,"") -> 927.50392 | J27: =I27 -> 927.50392 | L27: =((J27-Costs_init!J27)/Costs_init!J27) -> 0
B28: 008 | D28: Model auxiliary diagrams | E28: System Analyst | F28: 8 | G28: Hours | H28: =_xlfn.XLOOKUP(E28,$Q$20:$Q$25,$R$20:$R$25,"") -> 42.159269 | I28: =IFERROR(H28*F28,"") -> 337.27415 | J28: =I28 -> 337.27415 | L28: =((J28-Costs_init!J28)/Costs_init!J28) -> 0.33333333
B29: 009 | D29: Review software requirements | E29: System Analyst | F29: 4 | G29: Hours | H29: =_xlfn.XLOOKUP(E29,$Q$20:$Q$25,$R$20:$R$25,"") -> 42.159269 | I29: =IFERROR(H29*F29,"") -> 168.63708 | J29: =I29 -> 168.63708 | L29: =((J29-Costs_init!J29)/Costs_init!J29) -> 1
B30: 010 | D30: Modify requirements with feedback | E30: System Analyst | F30: 8 | G30: Hours | H30: =_xlfn.XLOOKUP(E30,$Q$20:$Q$25,$R$20:$R$25,"") -> 42.159269 | I30: =IFERROR(H30*F30,"") -> 337.27415 | J30: =I30 -> 337.27415 | L30: =((J30-Costs_init!J30)/Costs_init!J30) -> 0
A31: 03 | D31: Design | H31: =_xlfn.XLOOKUP(E31,$Q$20:$Q$25,$R$20:$R$25,"") | I31: =IFERROR(H31*F31,"") | K31: =SUM(J32:J38) -> 2361.0627 | L31: =((K31-Costs_init!K31)/Costs_init!K31) -> 0.038574169
B32: 001 | D32: Design architecture | E32: Software architect | F32: 10 | G32: Hours | H32: =_xlfn.XLOOKUP(E32,$Q$20:$Q$25,$R$20:$R$25,"") -> 49.154057 | I32: =IFERROR(H32*F32,"") -> 491.54057 | J32: =I32 -> 491.54057 | L32: =((J32-Costs_init!J32)/Costs_init!J32) -> 0
B33: 002 | D33: Design brand identity | E33: Junior software engineer | F33: 3 | G33: Hours | H33: =_xlfn.XLOOKUP(E33,$Q$20:$Q$25,$R$20:$R$25,"") -> 38.551814 | I33: =IFERROR(H33*F33,"") -> 115.65544 | J33: =I33 -> 115.65544 | L33: =((J33-Costs_init!J33)/Costs_init!J33) -> 0
B34: 003 | D34: Design project management | E34: Senior software engineer | F34: 8 | G34: Hours | H34: =_xlfn.XLOOKUP(E34,$Q$20:$Q$25,$R$20:$R$25,"") -> 43.846666 | I34: =IFERROR(H34*F34,"") -> 350.77333 | J34: =I34 -> 350.77333 | L34: =((J34-Costs_init!J34)/Costs_init!J34) -> 0
B35: 004 | D35: Design stakeholder management | E35: Senior software engineer | F35: 4 | G35: Hours | H35: =_xlfn.XLOOKUP(E35,$Q$20:$Q$25,$R$20:$R$25,"") -> 43.846666 | I35: =IFERROR(H35*F35,"") -> 175.38667 | J35: =I35 -> 175.38667 | L35: =((J35-Costs_init!J35)/Costs_init!J35) -> 0
B36: 005 | D36: Design requirement management | E36: Senior software engineer | F36: 6 | G36: Hours | H36: =_xlfn.XLOOKUP(E36,$Q$20:$Q$25,$R$20:$R$25,"") -> 43.846666 | I36: =IFERROR(H36*F36,"") -> 263.08 | J36: =I36 -> 263.08 | L36: =((J36-Costs_init!J36)/Costs_init!J36) -> 0
B37: 006 | D37: Design user management | E37: Senior software engineer | F37: 12 | G37: Hours | H37: =_xlfn.XLOOKUP(E37,$Q$20:$Q$25,$R$20:$R$25,"") -> 43.846666 | I37: =IFERROR(H37*F37,"") -> 526.16 | J37: =I37 -> 526.16 | L37: =((J37-Costs_init!J37)/Costs_init!J37) -> 0.2
B38: 007 | D38: Design document management | E38: Senior software engineer | F38: 10 | G38: Hours | H38: =_xlfn.XLOOKUP(E38,$Q$20:$Q$25,$R$20:$R$25,"") -> 43.846666 | I38: =IFERROR(H38*F38,"") -> 438.46666 | J38: =I38 -> 438.46666 | L38: =((J38-Costs_init!J38)/Costs_init!J38) -> 0
A39: 04 | D39: Set up SonarQube for Quality Assurance | E39: Senior software engineer | F39: 6 | G39: Hours | H39: =_xlfn.XLOOKUP(E39,$Q$20:$Q$25,$R$20:$R$25,"") -> 43.846666 | I39: =IFERROR(H39*F39,"") -> 263.08 | J39: =SUM(I39) -> 263.08 | K39: =SUM(J39) -> 263.08 | L39: =((K39-Costs_init!K39)/Costs_init!K39) -> 1
A40: 05 | D40: Development | H40: =_xlfn.XLOOKUP(E40,$Q$20:$Q$25,$R$20:$R$25,"") | I40: =IFERROR(H40*F40,"") | K40: =SUM(J41:J50) -> 4485.1818 | L40: =((K40-Costs_init!K40)/Costs_init!K40) -> 0.022403762
B41: 001 | D41: Set up architecture | E41: Software architect | F41: 6 | G41: Hours | H41: =_xlfn.XLOOKUP(E41,$Q$20:$Q$25,$R$20:$R$25,"") -> 49.154057 | I41: =IFERROR(H41*F41,"") -> 294.92434 | J41: =I41 -> 294.92434 | L41: =((J41-Costs_init!J41)/Costs_init!J41) -> 0.5
B42: 002 | D42: Set up development enviroment | E42: Software architect | F42: 1 | G42: Hours | H42: =_xlfn.XLOOKUP(E42,$Q$20:$Q$25,$R$20:$R$25,"") -> 49.154057 | I42: =IFERROR(H42*F42,"") -> 49.154057 | J42: =I42 -> 49.154057 | L42: =((J42-Costs_init!J42)/Costs_init!J42) -> -0.66666667
B43: 003 | D43: Develop code | H43: =_xlfn.XLOOKUP(E43,$Q$20:$Q$25,$R$20:$R$25,"") | I43: =IFERROR(H43*F43,"") | J43: =SUM(I44:I50) -> 4141.1034 | L43: =((J43-Costs_init!J43)/Costs_init!J43) -> 0.024310513
C44: 01 | D44: Develop project management module | E44: Junior software engineer | F44: 22 | G44: Hours | H44: =_xlfn.XLOOKUP(E44,$Q$20:$Q$25,$R$20:$R$25,"") -> 38.551814 | I44: =IFERROR(H44*F44,"") -> 848.13991 | L44: =((I44-Costs_init!I44)/Costs_init!I44) -> 0
C45: 02 | D45: Develop stakeholder management module | E45: Junior software engineer | F45: 6 | G45: Hours | H45: =_xlfn.XLOOKUP(E45,$Q$20:$Q$25,$R$20:$R$25,"") -> 38.551814 | I45: =IFERROR(H45*F45,"") -> 231.31089 | L45: =((I45-Costs_init!I45)/Costs_init!I45) -> -0.4
C46: 03 | D46: Develop requirement management module | E46: Senior software engineer | F46: 24 | G46: Hours | H46: =_xlfn.XLOOKUP(E46,$Q$20:$Q$25,$R$20:$R$25,"") -> 43.846666 | I46: =IFERROR(H46*F46,"") -> 1052.32 | L46: =((I46-Costs_init!I46)/Costs_init!I46) -> -0.04
C47: 04 | D47: Develop user management module | E47: Junior software engineer | F47: 12 | G47: Hours | H47: =_xlfn.XLOOKUP(E47,$Q$20:$Q$25,$R$20:$R$25,"") -> 38.551814 | I47: =IFERROR(H47*F47,"") -> 462.62177 | L47: =((I47-Costs_init!I47)/Costs_init!I47) -> 1
C48: 05 | D48: Develop document management | E48: Senior software engineer | F48: 20 | G48: Hours | H48: =_xlfn.XLOOKUP(E48,$Q$20:$Q$25,$R$20:$R$25,"") -> 43.846666 | I48: =IFERROR(H48*F48,"") -> 876.93333 | L48: =((I48-Costs_init!I48)/Costs_init!I48) -> 0.33333333
C49: 06 | D49: Develop modifying concurrency system | E49: Senior software engineer | F49: 10 | G49: Hours | H49: =_xlfn.XLOOKUP(E49,$Q$20:$Q$25,$R$20:$R$25,"") -> 43.846666 | I49: =IFERROR(H49*F49,"") -> 438.46666 | L49: =((I49-Costs_init!I49)/Costs_init!I49) -> 0
C50: 07 | D50: Develop search and filtering | E50: Junior software engineer | F50: 6 | G50: Hours | H50: =_xlfn.XLOOKUP(E50,$Q$20:$Q$25,$R$20:$R$25,"") -> 38.551814 | I50: =IFERROR(H50*F50,"") -> 231.31089 | L50: =((I50-Costs_init!I50)/Costs_init!I50) -> -0.4
A51: 06 | D51: Testing | H51: =_xlfn.XLOOKUP(E51,$Q$20:$Q$25,$R$20:$R$25,"") | I51: =IFERROR(H51*F51,"") | K51: =SUM(J52:J60) -> 1359.9032 | L51: =((K51-Costs_init!K51)/Costs_init!K51) -> 0.29331225
B52: 001 | D52: Test project management module | E52: Junior software engineer | F52: 6 | G52: Hours | H52: =_xlfn.XLOOKUP(E52,$Q$20:$Q$25,$R$20:$R$25,"") -> 38.551814 | I52: =IFERROR(H52*F52,"") -> 231.31089 | J52: =I52 -> 231.31089 | L52: =((J52-Costs_init!J52)/Costs_init!J52) -> 0.5
B53: 002 | D53: Test stakeholder management module | E53: Junior software engineer | F53: 4 | G53: Hours | H53: =_xlfn.XLOOKUP(E53,$Q$20:$Q$25,$R$20:$R$25,"") -> 38.551814 | I53: =IFERROR(H53*F53,"") -> 154.20726 | J53: =I53 -> 154.20726 | L53: =((J53-Costs_init!J53)/Costs_init!J53) -> 0.33333333
B54: 003 | D54: Test requirement management module | E54: Junior software engineer | F54: 5 | G54: Hours | H54: =_xlfn.XLOOKUP(E54,$Q$20:$Q$25,$R$20:$R$25,"") -> 38.551814 | I54: =IFERROR(H54*F54,"") -> 192.75907 | J54: =I54 -> 192.75907 | L54: =((J54-Costs_init!J54)/Costs_init!J54) -> 0
B55: 004 | D55: Test user management module | E55: Junior software engineer | F55: 3 | G55: Hours | H55: =_xlfn.XLOOKUP(E55,$Q$20:$Q$25,$R$20:$R$25,"") -> 38.551814 | I55: =IFERROR(H55*F55,"") -> 115.65544 | J55: =I55 -> 115.65544 | L55: =((J55-Costs_init!J55)/Costs_init!J55) -> 0
B56: 005 | D56: Test document management | E56: Junior software engineer | F56: 4 | G56: Hours | H56: =_xlfn.XLOOKUP(E56,$Q$20:$Q$25,$R$20:$R$25,"") -> 38.551814 | I56: =IFERROR(H56*F56,"") -> 154.20726 | J56: =I56 -> 154.20726 | L56: =((J56-Costs_init!J56)/Costs_init!J56) -> 0.33333333
B57: 006 | D57: Test modifying concurrency system | E57: Junior software engineer | F57: 5 | G57: Hours | H57: =_xlfn.XLOOKUP(E57,$Q$20:$Q$25,$R$20:$R$25,"") -> 38.551814 | I57: =IFERROR(H57*F57,"") -> 192.75907 | J57: =I57 -> 192.75907 | L57: =((J57-Costs_init!J57)/Costs_init!J57) -> 1.5
B58: 007 | D58: Test search and filtering | E58: Junior software engineer | F58: 3 | G58: Hours | H58: =_xlfn.XLOOKUP(E58,$Q$20:$Q$25,$R$20:$R$25,"") -> 38.551814 | I58: =IFERROR(H58*F58,"") -> 115.65544 | J58: =I58 -> 115.65544 | L58: =((J58-Costs_init!J58)/Costs_init!J58) -> 0
B59: 008 | D59: Usability and accesibility testing | E59: Junior software engineer | F59: 3 | G59: Hours | H59: =_xlfn.XLOOKUP(E59,$Q$20:$Q$25,$R$20:$R$25,"") -> 38.551814 | I59: =IFERROR(H59*F59,"") -> 115.65544 | J59: =I59 -> 115.65544 | L59: =((J59-Costs_init!J59)/Costs_init!J59) -> 0.5
B60: 009 | D60: Load testing | E60: Senior software engineer | F60: 2 | G60: Hours | H60: =_xlfn.XLOOKUP(E60,$Q$20:$Q$25,$R$20:$R$25,"") -> 43.846666 | I60: =IFERROR(H60*F60,"") -> 87.693333 | J60: =I60 -> 87.693333 | L60: =((J60-Costs_init!J60)/Costs_init!J60) -> 0
A61: 07 | D61: Documentation | H61: =_xlfn.XLOOKUP(E61,$Q$20:$Q$25,$R$20:$R$25,"") | I61: =IFERROR(H61*F61,"") | K61: =SUM(J62:J73) -> 1285.9236 | L61: =((K61-Costs_init!K61)/Costs_init!K61) -> -0.069886161
B62: 001 | D62: Document declaration of originality, abstract and keywords | E62: Project manager | F62: 1 | G62: Hours | H62: =_xlfn.XLOOKUP(E62,$Q$20:$Q$25,$R$20:$R$25,"") -> 49.782125 | I62: =IFERROR(H62*F62,"") -> 49.782125 | J62: =I62 -> 49.782125 | L62: =((J62-Costs_init!J62)/Costs_init!J62) -> 0
B63: 002 | D63: Document introduction | E63: Project manager | F63: 1 | G63: Hours | H63: =_xlfn.XLOOKUP(E63,$Q$20:$Q$25,$R$20:$R$25,"") -> 49.782125 | I63: =IFERROR(H63*F63,"") -> 49.782125 | J63: =I63 -> 49.782125 | L63: =((J63-Costs_init!J63)/Costs_init!J63) -> 0
B64: 003 | D64: Document theoretical background | E64: Technology consultant | F64: 1 | G64: Hours | H64: =_xlfn.XLOOKUP(E64,$Q$20:$Q$25,$R$20:$R$25,"") -> 45.220459 | I64: =IFERROR(H64*F64,"") -> 45.220459 | J64: =I64 -> 45.220459 | L64: =((J64-Costs_init!J64)/Costs_init!J64) -> 0
B65: 004 | D65: Document feasibility study and alternative analysis | E65: Technology consultant | F65: 2 | G65: Hours | H65: =_xlfn.XLOOKUP(E65,$Q$20:$Q$25,$R$20:$R$25,"") -> 45.220459 | I65: =IFERROR(H65*F65,"") -> 90.440919 | J65: =I65 -> 90.440919 | L65: =((J65-Costs_init!J65)/Costs_init!J65) -> 0
B66: 005 | D66: Document Initial project planning and management | E66: Project manager | F66: 3 | G66: Hours | H66: =_xlfn.XLOOKUP(E66,$Q$20:$Q$25,$R$20:$R$25,"") -> 49.782125 | I66: =IFERROR(H66*F66,"") -> 149.34638 | J66: =I66 -> 149.34638 | L66: =((J66-Costs_init!J66)/Costs_init!J66) -> 0.5
B67: 006 | D67: Document system analysis | E67: System Analyst | F67: 2 | G67: Hours | H67: =_xlfn.XLOOKUP(E67,$Q$20:$Q$25,$R$20:$R$25,"") -> 42.159269 | I67: =IFERROR(H67*F67,"") -> 84.318538 | J67: =I67 -> 84.318538 | L67: =((J67-Costs_init!J67)/Costs_init!J67) -> -0.33333333
B68: 007 | D68: Document system design | E68: Software architect | F68: 3 | G68: Hours | H68: =_xlfn.XLOOKUP(E68,$Q$20:$Q$25,$R$20:$R$25,"") -> 49.154057 | I68: =IFERROR(H68*F68,"") -> 147.46217 | J68: =I68 -> 147.46217 | L68: =((J68-Costs_init!J68)/Costs_init!J68) -> -0.4
B69: 008 | D69: Document system implementation | E69: Senior software engineer | F69: 6 | G69: Hours | H69: =_xlfn.XLOOKUP(E69,$Q$20:$Q$25,$R$20:$R$25,"") -> 43.846666 | I69: =IFERROR(H69*F69,"") -> 263.08 | J69: =I69 -> 263.08 | L69: =((J69-Costs_init!J69)/Costs_init!J69) -> 0.2
B70: 009 | D70: Document test plan execution | E70: Senior software engineer | F70: 2 | G70: Hours | H70: =_xlfn.XLOOKUP(E70,$Q$20:$Q$25,$R$20:$R$25,"") -> 43.846666 | I70: =IFERROR(H70*F70,"") -> 87.693333 | J70: =I70 -> 87.693333 | L70: =((J70-Costs_init!J70)/Costs_init!J70) -> 0
B71: 010 | D71: Document system manuals | E71: Senior software engineer | F71: 5 | G71: Hours | H71: =_xlfn.XLOOKUP(E71,$Q$20:$Q$25,$R$20:$R$25,"") -> 43.846666 | I71: =IFERROR(H71*F71,"") -> 219.23333 | J71: =I71 -> 219.23333 | L71: =((J71-Costs_init!J71)/Costs_init!J71) -> 0
B72: 011 | D72: Document final project closure | E72: Project manager | F72: 1 | G72: Hours | H72: =_xlfn.XLOOKUP(E72,$Q$20:$Q$25,$R$20:$R$25,"") -> 49.782125 | I72: =IFERROR(H72*F72,"") -> 49.782125 | J72: =I72 -> 49.782125 | L72: =((J72-Costs_init!J72)/Costs_init!J72) -> -0.5
B73: 012 | D73: Document conclusions and future work | E73: Project manager | F73: 1 | G73: Hours | H73: =_xlfn.XLOOKUP(E73,$Q$20:$Q$25,$R$20:$R$25,"") -> 49.782125 | I73: =IFERROR(H73*F73,"") -> 49.782125 | J73: =I73 -> 49.782125 | L73: =((J73-Costs_init!J73)/Costs_init!J73) -> 0
A74: Total | K74: =SUM(K3:K73) -> 13383.613 | L74: =((K74-Costs_init!K74)/Costs_init!K74) -> 0.027412946
A76: Category 2: Other
A77: I1 | B77: I2 | C77: I3 | D77: Description | E77: Resource | F77: Cuantity | G77: Units | H77: Price | I77: Subtotal | J77: Subtotal (2) | K77: Total
A78: 01 | D78: Travel and transportation expenses | J78: =SUM(I79:I80) -> 172.5 | K78: =J78 -> 172.5
B79: 001 | D79: Travel to client facilities (deployment/support) | E79: - | F79: 150 | G79: km | H79: 0.35 | I79: =H79*F79 -> 52.5
B80: 002 | D80: Meals/daily allowance | E80: - | F80: 6 | G80: meals | H80: 20 | I80: =H80*F80 -> 120
A81: Total | K81: =SUM(K78:K80) -> 172.5
